ckan_crawler/__init__.py
ckan_crawler/main.py
ckan_crawler-0.1.15.dist-info/entry_points.txt
ckan_crawler-0.1.15.dist-info/LICENSE
ckan_crawler-0.1.15.dist-info/WHEEL
ckan_crawler-0.1.15.dist-info/METADATA
ckan_crawler-0.1.15.dist-info/RECORD
