Metadata-Version: 2.1
Name: ckan-crawler
Version: 0.1.15
Summary: 
Author: Lucas Bellomo
Author-email: lbellomo@gmail.com
Requires-Python: >=3.8,<4.0
Classifier: Programming Language :: Python :: 3
Classifier: Programming Language :: Python :: 3.8
Requires-Dist: requests (>=2.24.0,<3.0.0)
Requires-Dist: toml (>=0.10.1,<0.11.0)
